odoo/addons/edi_partner_oca/README.rst
odoo/addons/edi_partner_oca/__init__.py
odoo/addons/edi_partner_oca/__manifest__.py
odoo/addons/edi_partner_oca/i18n/de.po
odoo/addons/edi_partner_oca/i18n/edi_partner_oca.pot
odoo/addons/edi_partner_oca/i18n/it.po
odoo/addons/edi_partner_oca/models/__init__.py
odoo/addons/edi_partner_oca/models/res_partner.py
odoo/addons/edi_partner_oca/readme/CONTRIBUTORS.rst
odoo/addons/edi_partner_oca/readme/CREDITS.rst
odoo/addons/edi_partner_oca/readme/DESCRIPTION.rst
odoo/addons/edi_partner_oca/static/description/icon.png
odoo/addons/edi_partner_oca/static/description/index.html
odoo/addons/edi_partner_oca/views/partner_views.xml
odoo_addon_edi_partner_oca-16.0.1.0.1.11.dist-info/METADATA
odoo_addon_edi_partner_oca-16.0.1.0.1.11.dist-info/WHEEL
odoo_addon_edi_partner_oca-16.0.1.0.1.11.dist-info/top_level.txt
odoo_addon_edi_partner_oca-16.0.1.0.1.11.dist-info/RECORD
